python_paypal_api/__init__.py
python_paypal_api/version.py
python_paypal_api/api/__init__.py
python_paypal_api/api/disputes.py
python_paypal_api/api/identity.py
python_paypal_api/api/invoices.py
python_paypal_api/api/orders.py
python_paypal_api/api/partner_referrals.py
python_paypal_api/api/products.py
python_paypal_api/api/tracking.py
python_paypal_api/api/transactions.py
python_paypal_api/auth/__init__.py
python_paypal_api/auth/access_token_client.py
python_paypal_api/auth/access_token_response.py
python_paypal_api/auth/credentials.py
python_paypal_api/auth/exceptions.py
python_paypal_api/base/__init__.py
python_paypal_api/base/api_response.py
python_paypal_api/base/base_client.py
python_paypal_api/base/client.py
python_paypal_api/base/config.py
python_paypal_api/base/credential_provider.py
python_paypal_api/base/enum.py
python_paypal_api/base/exceptions.py
python_paypal_api/base/helpers.py
python_paypal_api/base/utils.py
python_paypal_api-0.1.2.dist-info/LICENSE
python_paypal_api-0.1.2.dist-info/METADATA
python_paypal_api-0.1.2.dist-info/WHEEL
python_paypal_api-0.1.2.dist-info/top_level.txt
python_paypal_api-0.1.2.dist-info/RECORD
