Metadata-Version: 2.1
Name: python-paypal-api
Version: 0.1.2
Summary: Paypal Python 3 API integration
Home-page: https://github.com/denisneuf/python_paypal_api
Author: denisneuf
Author-email: denisneuf@hotmail.com
License: Apache License 2.0
Classifier: License :: OSI Approved :: Apache Software License
Classifier: Programming Language :: Python :: 3
Requires-Python: >=3.8
License-File: LICENSE
